huggingface_urls/__init__.py
huggingface_urls/parse_hub.py
huggingface_urls-0.1.dist-info/METADATA
huggingface_urls-0.1.dist-info/WHEEL
huggingface_urls-0.1.dist-info/top_level.txt
huggingface_urls-0.1.dist-info/RECORD
